[ {
  "date" : "20160528",
  "segments" : [ {
    "type" : "place",
    "startTime" : "20160527T205550+0900",
    "endTime" : "20160528T200659+0900",
    "place" : {
      "id" : 257240275,
      "type" : "unknown",
      "location" : {
        "lat" : 43.084886,
        "lon" : 141.3453
      }
    },
    "lastUpdate" : "20160528T111944Z"
  }, {
    "type" : "place",
    "startTime" : "20160528T200853+0900",
    "endTime" : "20160528T205729+0900",
    "place" : {
      "id" : 261061610,
      "type" : "unknown",
      "location" : {
        "lat" : 43.082159,
        "lon" : 141.3468
      }
    },
    "lastUpdate" : "20160528T125155Z"
  } ],
  "lastUpdate" : "20160528T125155Z"
} ]