[ {
  "date" : "20140929",
  "segments" : [ {
    "type" : "place",
    "startTime" : "20140929T150251+0900",
    "endTime" : "20140929T150948+0900",
    "place" : {
      "id" : 98399034,
      "type" : "unknown",
      "location" : {
        "lat" : 35.7020375319,
        "lon" : 139.7454184047
      }
    },
    "lastUpdate" : "20140929T090432Z"
  }, {
    "type" : "place",
    "startTime" : "20140929T161956+0900",
    "endTime" : "20140929T210345+0900",
    "place" : {
      "id" : 98399036,
      "type" : "unknown",
      "location" : {
        "lat" : 35.9175705819,
        "lon" : 139.9089836272
      }
    },
    "lastUpdate" : "20140929T180456Z"
  }, {
    "type" : "place",
    "startTime" : "20140929T215952+0900",
    "endTime" : "20140929T220408+0900",
    "place" : {
      "id" : 98460445,
      "type" : "unknown",
      "location" : {
        "lat" : 35.6981857759,
        "lon" : 139.7734817711
      }
    },
    "lastUpdate" : "20140929T180456Z"
  }, {
    "type" : "place",
    "startTime" : "20140929T222802+0900",
    "endTime" : "20140930T113612+0900",
    "place" : {
      "id" : 98345442,
      "type" : "unknown",
      "location" : {
        "lat" : 35.7168392789,
        "lon" : 139.7283806079
      }
    },
    "lastUpdate" : "20140930T061040Z"
  } ],
  "lastUpdate" : "20140930T061040Z"
} ]