[ {
  "date" : "20170406",
  "summary" : [ {
    "activity" : "walking",
    "group" : "walking",
    "duration" : 1839.0,
    "distance" : 1838.0,
    "steps" : 2610,
    "calories" : 102
  }, {
    "activity" : "transport",
    "group" : "transport",
    "duration" : 267.0,
    "distance" : 1284.0
  }, {
    "activity" : "cycling",
    "group" : "cycling",
    "duration" : 438.0,
    "distance" : 1172.0,
    "calories" : 31
  } ],
  "caloriesIdle" : 1596,
  "lastUpdate" : "20170407T012724Z"
} ]