[ {
  "date" : "20160323",
  "summary" : [ {
    "activity" : "walking",
    "group" : "walking",
    "duration" : 3230.0,
    "distance" : 3355.0,
    "steps" : 4836,
    "calories" : 187
  }, {
    "activity" : "transport",
    "group" : "transport",
    "duration" : 3710.0,
    "distance" : 35859.0
  }, {
    "activity" : "running",
    "group" : "running",
    "duration" : 536.0,
    "distance" : 1564.0,
    "steps" : 1296,
    "calories" : 105
  } ],
  "segments" : [ {
    "type" : "place",
    "startTime" : "20160322T232550+0900",
    "endTime" : "20160323T110739+0900",
    "activities" : [ {
      "activity" : "walking",
      "group" : "walking",
      "manual" : false,
      "startTime" : "20160323T110356+0900",
      "endTime" : "20160323T111205+0900",
      "duration" : 489.0,
      "distance" : 489.0,
      "steps" : 652,
      "calories" : 27
    } ],
    "lastUpdate" : "20160323T044304Z"
  }, {
    "type" : "move",
    "startTime" : "20160323T110739+0900",
    "endTime" : "20160323T114150+0900",
    "activities" : [ {
      "activity" : "running",
      "group" : "running",
      "manual" : false,
      "startTime" : "20160323T110739+0900",
      "endTime" : "20160323T111335+0900",
      "duration" : 356.0,
      "distance" : 1035.0,
      "steps" : 846,
      "calories" : 70
    }, {
      "activity" : "transport",
      "group" : "transport",
      "manual" : false,
      "startTime" : "20160323T111335+0900",
      "endTime" : "20160323T112535+0900",
      "duration" : 720.0,
      "distance" : 4682.0
    }, {
      "activity" : "running",
      "group" : "running",
      "manual" : false,
      "startTime" : "20160323T112536+0900",
      "endTime" : "20160323T112836+0900",
      "duration" : 180.0,
      "distance" : 529.0,
      "steps" : 450,
      "calories" : 36
    }, {
      "activity" : "walking",
      "group" : "walking",
      "manual" : false,
      "startTime" : "20160323T112836+0900",
      "endTime" : "20160323T114150+0900",
      "duration" : 794.0,
      "distance" : 931.0,
      "steps" : 1158,
      "calories" : 52
    } ],
    "lastUpdate" : "20160323T044304Z"
  }, {
    "type" : "place",
    "startTime" : "20160323T114150+0900",
    "endTime" : "20160323T214632+0900",
    "activities" : [ {
      "activity" : "walking",
      "group" : "walking",
      "manual" : false,
      "startTime" : "20160323T114156+0900",
      "endTime" : "20160323T114512+0900",
      "duration" : 196.0,
      "distance" : 215.0,
      "steps" : 287,
      "calories" : 12
    }, {
      "activity" : "walking",
      "group" : "walking",
      "manual" : false,
      "startTime" : "20160323T120053+0900",
      "endTime" : "20160323T120133+0900",
      "duration" : 40.0,
      "distance" : 27.0,
      "steps" : 54,
      "calories" : 2
    }, {
      "activity" : "walking",
      "group" : "walking",
      "manual" : false,
      "startTime" : "20160323T192023+0900",
      "endTime" : "20160323T192138+0900",
      "duration" : 75.0,
      "distance" : 50.0,
      "steps" : 100,
      "calories" : 3
    }, {
      "activity" : "walking",
      "group" : "walking",
      "manual" : false,
      "startTime" : "20160323T200336+0900",
      "endTime" : "20160323T200428+0900",
      "duration" : 52.0,
      "distance" : 34.0,
      "steps" : 69,
      "calories" : 2
    }, {
      "activity" : "walking",
      "group" : "walking",
      "manual" : false,
      "startTime" : "20160323T210000+0900",
      "endTime" : "20160323T210444+0900",
      "duration" : 284.0,
      "distance" : 316.0,
      "steps" : 422,
      "calories" : 18
    } ],
    "lastUpdate" : "20160323T140115Z"
  }, {
    "type" : "move",
    "startTime" : "20160323T214632+0900",
    "endTime" : "20160323T225406+0900",
    "activities" : [ {
      "activity" : "walking",
      "group" : "walking",
      "manual" : false,
      "startTime" : "20160323T214632+0900",
      "endTime" : "20160323T215638+0900",
      "duration" : 606.0,
      "distance" : 581.0,
      "steps" : 893,
      "calories" : 32
    }, {
      "activity" : "transport",
      "group" : "transport",
      "manual" : false,
      "startTime" : "20160323T215639+0900",
      "endTime" : "20160323T224629+0900",
      "duration" : 2990.0,
      "distance" : 31177.0
    }, {
      "activity" : "walking",
      "group" : "walking",
      "manual" : false,
      "startTime" : "20160323T224629+0900",
      "endTime" : "20160323T225405+0900",
      "duration" : 456.0,
      "distance" : 427.0,
      "steps" : 797,
      "calories" : 24
    } ],
    "lastUpdate" : "20160323T140115Z"
  }, {
    "type" : "place",
    "startTime" : "20160323T225406+0900",
    "endTime" : "20160324T102445+0900",
    "activities" : [ {
      "activity" : "walking",
      "group" : "walking",
      "manual" : false,
      "startTime" : "20160323T225406+0900",
      "endTime" : "20160323T225725+0900",
      "duration" : 199.0,
      "distance" : 251.0,
      "steps" : 335,
      "calories" : 14
    }, {
      "activity" : "walking",
      "group" : "walking",
      "manual" : false,
      "startTime" : "20160323T230000+0900",
      "endTime" : "20160323T230039+0900",
      "duration" : 39.0,
      "distance" : 34.0,
      "steps" : 69,
      "calories" : 2
    } ],
    "lastUpdate" : "20160324T021939Z"
  } ],
  "caloriesIdle" : 1601,
  "lastUpdate" : "20160324T021939Z"
} ]