[ {
  "date" : "20160831",
  "summary" : [ {
    "activity" : "walking",
    "group" : "walking",
    "duration" : 1859.0,
    "distance" : 2442.0,
    "steps" : 2889,
    "calories" : 136
  } ],
  "segments" : [ {
    "type" : "place",
    "startTime" : "20160830T163520+0900",
    "endTime" : "20160831T150130+0900",
    "activities" : [ {
      "activity" : "walking",
      "group" : "walking",
      "manual" : false,
      "startTime" : "20160831T150124+0900",
      "endTime" : "20160831T150130+0900",
      "duration" : 6.0,
      "distance" : 4.0,
      "steps" : 8,
      "calories" : 0
    } ],
    "lastUpdate" : "20160831T073522Z"
  }, {
    "type" : "move",
    "startTime" : "20160831T150130+0900",
    "endTime" : "20160831T151629+0900",
    "activities" : [ {
      "activity" : "walking",
      "group" : "walking",
      "manual" : false,
      "startTime" : "20160831T150130+0900",
      "endTime" : "20160831T151629+0900",
      "duration" : 899.0,
      "distance" : 1131.0,
      "steps" : 1346,
      "calories" : 63
    } ],
    "lastUpdate" : "20160831T073522Z"
  }, {
    "type" : "place",
    "startTime" : "20160831T151630+0900",
    "endTime" : "20160831T193732+0900",
    "activities" : [ {
      "activity" : "walking",
      "group" : "walking",
      "manual" : false,
      "startTime" : "20160831T193553+0900",
      "endTime" : "20160831T193907+0900",
      "duration" : 194.0,
      "distance" : 234.0,
      "steps" : 312,
      "calories" : 13
    } ],
    "lastUpdate" : "20160831T121205Z"
  }, {
    "type" : "move",
    "startTime" : "20160831T193732+0900",
    "endTime" : "20160831T195012+0900",
    "activities" : [ {
      "activity" : "walking",
      "group" : "walking",
      "manual" : false,
      "startTime" : "20160831T193732+0900",
      "endTime" : "20160831T195012+0900",
      "duration" : 760.0,
      "distance" : 1073.0,
      "steps" : 1223,
      "calories" : 60
    } ],
    "lastUpdate" : "20160831T121205Z"
  } ],
  "caloriesIdle" : 1601,
  "lastUpdate" : "20160831T121205Z"
} ]