[ {
  "date" : "20170225",
  "summary" : [ {
    "activity" : "walking",
    "group" : "walking",
    "duration" : 2156.0,
    "distance" : 2019.0,
    "steps" : 2869,
    "calories" : 112
  }, {
    "activity" : "transport",
    "group" : "transport",
    "duration" : 3986.0,
    "distance" : 21676.0
  } ],
  "segments" : [ {
    "type" : "place",
    "startTime" : "20170224T233919+0900",
    "endTime" : "20170225T113440+0900",
    "activities" : [ {
      "activity" : "walking",
      "group" : "walking",
      "manual" : false,
      "startTime" : "20170225T112721+0900",
      "endTime" : "20170225T112807+0900",
      "duration" : 46.0,
      "distance" : 23.0,
      "steps" : 42,
      "calories" : 1
    } ],
    "lastUpdate" : "20170225T041540Z"
  }, {
    "type" : "move",
    "startTime" : "20170225T113440+0900",
    "endTime" : "20170225T121511+0900",
    "activities" : [ {
      "activity" : "transport",
      "group" : "transport",
      "manual" : false,
      "startTime" : "20170225T113440+0900",
      "endTime" : "20170225T115805+0900",
      "duration" : 1405.0,
      "distance" : 11391.0
    }, {
      "activity" : "walking",
      "group" : "walking",
      "manual" : false,
      "startTime" : "20170225T115806+0900",
      "endTime" : "20170225T120036+0900",
      "duration" : 150.0,
      "distance" : 133.0,
      "steps" : 267,
      "calories" : 7
    }, {
      "activity" : "transport",
      "group" : "transport",
      "manual" : false,
      "startTime" : "20170225T120036+0900",
      "endTime" : "20170225T121106+0900",
      "duration" : 630.0,
      "distance" : 1980.0
    }, {
      "activity" : "walking",
      "group" : "walking",
      "manual" : false,
      "startTime" : "20170225T121106+0900",
      "endTime" : "20170225T121510+0900",
      "duration" : 244.0,
      "distance" : 198.0,
      "steps" : 318,
      "calories" : 11
    } ],
    "lastUpdate" : "20170225T041540Z"
  }, {
    "type" : "place",
    "startTime" : "20170225T121511+0900",
    "endTime" : "20170225T181434+0900",
    "activities" : [ {
      "activity" : "walking",
      "group" : "walking",
      "manual" : false,
      "startTime" : "20170225T121511+0900",
      "endTime" : "20170225T121751+0900",
      "duration" : 160.0,
      "distance" : 173.0,
      "steps" : 231,
      "calories" : 10
    }, {
      "activity" : "walking",
      "group" : "walking",
      "manual" : false,
      "startTime" : "20170225T133448+0900",
      "endTime" : "20170225T133524+0900",
      "duration" : 36.0,
      "distance" : 24.0,
      "steps" : 48,
      "calories" : 1
    }, {
      "activity" : "walking",
      "group" : "walking",
      "manual" : false,
      "startTime" : "20170225T151900+0900",
      "endTime" : "20170225T152033+0900",
      "duration" : 93.0,
      "distance" : 66.0,
      "steps" : 132,
      "calories" : 4
    }, {
      "activity" : "walking",
      "group" : "walking",
      "manual" : false,
      "startTime" : "20170225T160013+0900",
      "endTime" : "20170225T160433+0900",
      "duration" : 260.0,
      "distance" : 265.0,
      "steps" : 354,
      "calories" : 15
    }, {
      "activity" : "walking",
      "group" : "walking",
      "manual" : false,
      "startTime" : "20170225T171029+0900",
      "endTime" : "20170225T171109+0900",
      "duration" : 40.0,
      "distance" : 27.0,
      "steps" : 54,
      "calories" : 1
    }, {
      "activity" : "walking",
      "group" : "walking",
      "manual" : false,
      "startTime" : "20170225T180542+0900",
      "endTime" : "20170225T180603+0900",
      "duration" : 21.0,
      "distance" : 14.0,
      "steps" : 28,
      "calories" : 1
    } ],
    "lastUpdate" : "20170225T103122Z"
  }, {
    "type" : "move",
    "startTime" : "20170225T181434+0900",
    "endTime" : "20170225T190048+0900",
    "activities" : [ {
      "activity" : "walking",
      "group" : "walking",
      "manual" : false,
      "startTime" : "20170225T181434+0900",
      "endTime" : "20170225T182118+0900",
      "duration" : 404.0,
      "distance" : 272.0,
      "steps" : 472,
      "calories" : 15
    }, {
      "activity" : "transport",
      "group" : "transport",
      "manual" : false,
      "startTime" : "20170225T182118+0900",
      "endTime" : "20170225T185349+0900",
      "duration" : 1951.0,
      "distance" : 8305.0
    }, {
      "activity" : "walking",
      "group" : "walking",
      "manual" : false,
      "startTime" : "20170225T185350+0900",
      "endTime" : "20170225T190048+0900",
      "duration" : 418.0,
      "distance" : 670.0,
      "steps" : 629,
      "calories" : 37
    } ],
    "lastUpdate" : "20170225T103122Z"
  }, {
    "type" : "place",
    "startTime" : "20170225T194600+0900",
    "endTime" : "20170225T230648+0900",
    "activities" : [ {
      "activity" : "walking",
      "group" : "walking",
      "manual" : false,
      "startTime" : "20170225T214947+0900",
      "endTime" : "20170225T214953+0900",
      "duration" : 6.0,
      "distance" : 4.0,
      "steps" : 8,
      "calories" : 0
    }, {
      "activity" : "walking",
      "group" : "walking",
      "manual" : false,
      "startTime" : "20170225T225906+0900",
      "endTime" : "20170225T225915+0900",
      "duration" : 9.0,
      "distance" : 6.0,
      "steps" : 13,
      "calories" : 0
    }, {
      "activity" : "walking",
      "group" : "walking",
      "manual" : false,
      "startTime" : "20170225T230200+0900",
      "endTime" : "20170225T230255+0900",
      "duration" : 55.0,
      "distance" : 37.0,
      "steps" : 74,
      "calories" : 2
    } ],
    "lastUpdate" : "20170226T104601Z"
  }, {
    "type" : "move",
    "startTime" : "20170225T230648+0900",
    "endTime" : "20170225T231434+0900",
    "activities" : [ {
      "activity" : "walking",
      "group" : "walking",
      "manual" : false,
      "startTime" : "20170225T230648+0900",
      "endTime" : "20170225T231012+0900",
      "duration" : 204.0,
      "distance" : 102.0,
      "steps" : 199,
      "calories" : 6
    } ],
    "lastUpdate" : "20170226T104601Z"
  }, {
    "type" : "off",
    "startTime" : "20170225T231434+0900",
    "endTime" : "20170226T181223+0900",
    "activities" : [ {
      "activity" : "walking",
      "group" : "walking",
      "manual" : false,
      "startTime" : "20170225T231443+0900",
      "endTime" : "20170225T231453+0900",
      "duration" : 10.0,
      "distance" : 5.0,
      "steps" : 0,
      "calories" : 0
    } ],
    "lastUpdate" : "20170226T104601Z"
  } ],
  "caloriesIdle" : 1596,
  "lastUpdate" : "20170226T104601Z"
} ]